cql/__init__.py
cql/__main__.py
cql/lexer.py
cql/parser.py
cql/py.typed
cql/_vendor/ply/__init__.py
cql/_vendor/ply/lex.py
cql/_vendor/ply/yacc.py
cql_parser-1.0.2.dist-info/METADATA
cql_parser-1.0.2.dist-info/WHEEL
cql_parser-1.0.2.dist-info/top_level.txt
cql_parser-1.0.2.dist-info/zip-safe
cql_parser-1.0.2.dist-info/RECORD
