Metadata-Version: 2.1
Name: cql-parser
Version: 1.0.2
Summary: "CQL (Contextual Query Language) Parser"
Home-page: https://github.com/Querela/cql-python/
Author: Erik Körner
Author-email: "Erik Körner" <koerner@saw-leipzig.de>
License: MIT
Project-URL: Source, https://github.com/Querela/cql-python/
Project-URL: Issue Tracker, https://github.com/Querela/cql-python/issues
Keywords: CQL,CLARIN,Query Parser
Classifier: Intended Audience :: Developers
Classifier: Intended Audience :: Science/Research
Classifier: License :: OSI Approved :: MIT License
Classifier: Operating System :: OS Independent
Classifier: Programming Language :: Python :: 3
Classifier: Programming Language :: Python :: 3 :: Only
Classifier: Programming Language :: Python :: 3.8
Classifier: Programming Language :: Python :: 3.9
Classifier: Programming Language :: Python :: 3.10
Classifier: Programming Language :: Python :: 3.11
Classifier: Programming Language :: Python :: 3.12
Classifier: Programming Language :: YACC
Classifier: Topic :: Text Processing :: General
Classifier: Topic :: Utilities
Requires-Python: >=3.8
Provides-Extra: build
Requires-Dist: build ; extra == 'build'
Requires-Dist: twine ; extra == 'build'
Provides-Extra: style
Requires-Dist: black ; extra == 'style'
Requires-Dist: flake8 ; extra == 'style'
Requires-Dist: isort ; extra == 'style'
Requires-Dist: mypy ; extra == 'style'
Provides-Extra: test
Requires-Dist: pytest ; extra == 'test'
Requires-Dist: pytest-cov ; extra == 'test'
Requires-Dist: pytest-clarity ; extra == 'test'
Requires-Dist: pytest-randomly ; extra == 'test'
Provides-Extra: vendor
Requires-Dist: vendoring ; extra == 'vendor'
